[
  {
    "dal_km": "5,500",
    "al_km": "77,500",
    "descrizione": "Lavori di manutenzione straordinaria per l`adeguamento delle barriere stradali lungo le Strade Statali SS.SS. 131in t.s.",
    "tipo_lavoro": "Lavori di manutenzione straordinaria.",
    "importo_lav_principali": "648.194,63",
    "importo_lav_totale": "691.208,42",
    "data_consegna_impresa": "05/12/2017",
    "avanzamento_lavori": "100,00",
    "ultimazione": "03/06/2018",
    "sospesa": "",
    "impresa": "ISEA S.R.L.",
    "id": "14121",
    "regione": "SARDEGNA",
    "strada": "SS131"
  },
  {
    "dal_km": "5,500",
    "al_km": "77,500",
    "descrizione": "Lavori di M.S.. Rifacimento dello strato di usura drenante previo rafforzamento localizzato della sovrastruttura stradale. compresa segnaletica orizzontale dal km 5+500 al km 77+500  SS 131 in t.s. ",
    "tipo_lavoro": "Lavori di manutenzione straordinaria.",
    "importo_lav_principali": "436.552,07",
    "importo_lav_totale": "446.699,86",
    "data_consegna_impresa": "04/06/2018",
    "avanzamento_lavori": "19,51",
    "ultimazione": "21/08/2018",
    "sospesa": "",
    "impresa": "IGECO COSTRUZIONI S.P.A",
    "id": "14128",
    "regione": "SARDEGNA",
    "strada": "SS131"
  },
  {
    "dal_km": "77,500",
    "al_km": "142,500",
    "descrizione": "SS.SS. del C.M. D - Lavori di M.S. - Lavori di distese generali. rafforzamento della pavimentazione stradale e opere marginali in tratti saltuari lungo la S.S. 131 ``Carlo Felice`` dal Km 77+500 al km 142+500.",
    "tipo_lavoro": "Lavori di manutenzione straordinaria.",
    "importo_lav_principali": "680.542,75",
    "importo_lav_totale": "708.651,45",
    "data_consegna_impresa": "13/03/2015",
    "avanzamento_lavori": "80,00",
    "ultimazione": "09/09/2015",
    "sospesa": "",
    "impresa": "SER.LU. COSTRUZIONI S.R.L.",
    "id": "14119",
    "regione": "SARDEGNA",
    "strada": "SS131"
  },
  {
    "dal_km": "77,500",
    "al_km": "142,500",
    "descrizione": "S.S. 131 ``Carlo Felice`` - Distese generali periodiche in conglomerato bituminoso drenante previo rafforzamento in piccoli tratti saltuari della sovrastruttura e adeguamento pendenze trasversali dal Km 77+500 al Km 142+500 in t.s.",
    "tipo_lavoro": "Lavori di manutenzione straordinaria.",
    "importo_lav_principali": "2.061.886,83",
    "importo_lav_totale": "2.140.907,96",
    "data_consegna_impresa": "26/10/2017",
    "avanzamento_lavori": "9,72",
    "ultimazione": "25/03/2018",
    "sospesa": "",
    "impresa": "IGECO COSTRUZIONI S.P.A",
    "id": "14123",
    "regione": "SARDEGNA",
    "strada": "SS131"
  },
  {
    "dal_km": "142,500",
    "al_km": "229,843",
    "descrizione": "Lavori di adeguamento della segnaletica verticale e marginale alle normative di sicurezza lungo la S.S. 131 dal km 142+500 al Km 229+843.",
    "tipo_lavoro": "Lavori di manutenzione straordinaria.",
    "importo_lav_principali": "255.065,22",
    "importo_lav_totale": "272.363,03",
    "data_consegna_impresa": "23/07/2018",
    "avanzamento_lavori": "0,00",
    "ultimazione": "20/10/2018",
    "sospesa": "",
    "impresa": "ATI SI.SE. SPA - VIS MOBILITY - INT CONS.",
    "id": "14130",
    "regione": "SARDEGNA",
    "strada": "SS131"
  },
  {
    "dal_km": "152,000",
    "al_km": "160,000",
    "descrizione": "Lavori di M.S. Distese con conglomerati bituminosi. previo rafforzamento della sovrastruttura stradale e compresa segnaletica orizzontale dal Km 149+000 al Km 161+000 S.S. 131.",
    "tipo_lavoro": "Lavori di manutenzione straordinaria.",
    "importo_lav_principali": "2.964.881,40",
    "importo_lav_totale": "3.082.372,48",
    "data_consegna_impresa": "25/05/2017",
    "avanzamento_lavori": "99,59",
    "ultimazione": "18/01/2018",
    "sospesa": "",
    "impresa": "IGECO COSTRUZIONI S.P.A",
    "id": "14125",
    "regione": "SARDEGNA",
    "strada": "SS131"
  },
  {
    "dal_km": "164,500",
    "al_km": "228,200",
    "descrizione": "S.S. 131 - Lavori di M.S. Ripristino della funzionalita dei giunti di dilatazione in corrispondenza dei viadotti ``Rio Molino`` al km 164+500. ``Landrigga``. ai km 215+300 e 215+500. e ``Riu Mannu``. al km 228+020.",
    "tipo_lavoro": "Lavori di manutenzione straordinaria.",
    "importo_lav_principali": "556.211,82",
    "importo_lav_totale": "615.965,09",
    "data_consegna_impresa": "09/03/2018",
    "avanzamento_lavori": "75,14",
    "ultimazione": "06/06/2018",
    "sospesa": "",
    "impresa": "COSPIN SRL",
    "id": "14135",
    "regione": "SARDEGNA",
    "strada": "SS131"
  },
  {
    "dal_km": "221,300",
    "al_km": "229,843",
    "descrizione": "Lavori di M.S. Rafforzamento della sovrastruttura stradale. compreso nuovo impianto di segnaletica orizzontale lungo la S.S. 131 dal Km 221+300 al Km 229+843.",
    "tipo_lavoro": "Lavori di manutenzione straordinaria.",
    "importo_lav_principali": "2.509.156,25",
    "importo_lav_totale": "2.633.696,88",
    "data_consegna_impresa": "28/11/2017",
    "avanzamento_lavori": "19,54",
    "ultimazione": "26/04/2018",
    "sospesa": "",
    "impresa": "IGECO COSTRUZIONI S.P.A",
    "id": "14131",
    "regione": "SARDEGNA",
    "strada": "SS131"
  }
]
