[
  {
    "dal_km": "0,000",
    "al_km": "0,000",
    "descrizione": "Itinerario NORD - SUD S. Stefano di Camastra - Gela. \r\nSS 117 Centrale Sicula - Lavori di ammodernamento e sistemazione del tratto compreso tra km 32+000 e km 38+700 della SS 117 - Lotto B4b",
    "tipo_lavoro": "Lavori straordinari per nuove costruzioni.",
    "importo_lav_principali": "65.065.789,37",
    "importo_lav_totale": "69.859.574,01",
    "data_consegna_impresa": "22/06/2011",
    "avanzamento_lavori": "90,93",
    "ultimazione": "17/09/2018",
    "sospesa": "",
    "impresa": "RICCIARDELLO COSTRUZIONI SRL",
    "id": "14339",
    "regione": "SICILIA",
    "strada": "ISV3"
  }
]
